helmet/__init__.py
helmet/explainers/__init__.py
helmet/explainers/gradients.py
helmet/explainers/perturbation.py
helmet/model/__init__.py
helmet/model/base_lm.py
helmet/model/dec_lm.py
helmet/updater.py
helmet/utils/constants.py
helmet/utils/types.py
helmet/utils/utils.py
helmet-1.1.1.dist-info/METADATA
helmet-1.1.1.dist-info/WHEEL
helmet-1.1.1.dist-info/RECORD
