Metadata-Version: 2.1
Name: helmet
Version: 1.1.1
Summary: 
Author: Jeroen
Requires-Python: >=3.10,<4.0
Classifier: Programming Language :: Python :: 3
Classifier: Programming Language :: Python :: 3.10
Classifier: Programming Language :: Python :: 3.11
Classifier: Programming Language :: Python :: 3.12
Requires-Dist: accelerate (>=0.25.0,<0.26.0)
Requires-Dist: bitsandbytes (>=0.42.0,<0.43.0)
Requires-Dist: dacite (>=1.8.1,<2.0.0)
Requires-Dist: datasets (>=2.18.0,<3.0.0)
Requires-Dist: numpy (>=1.26.2,<2.0.0)
Requires-Dist: torch (>=2.1.1,<3.0.0)
Requires-Dist: transformers (>=4.35.2,<5.0.0)
